bmi270/BMI270.py
bmi270/config_file.py
bmi270/definitions.py
bmi270/registers.py
bmi270-0.4.3.dist-info/LICENSE
bmi270-0.4.3.dist-info/METADATA
bmi270-0.4.3.dist-info/WHEEL
bmi270-0.4.3.dist-info/top_level.txt
bmi270-0.4.3.dist-info/RECORD
