Metadata-Version: 2.1
Name: bmi270
Version: 0.4.3
Summary: BMI270 I2C Python library (bare bones)
Author-email: Kevin Sommler <sommler@live.de>
License: MIT
Project-URL: Homepage, https://github.com/CoRoLab-Berlin/bmi270_python
Project-URL: Bug Tracker, https://github.com/CoRoLab-Berlin/bmi270_python/issues
Keywords: BMI270,I2C,IMU,sensor,driver,accelerometer,gyroscope,gyro,bosch,sensortech,smbus2,library
Classifier: Programming Language :: Python :: 3
Classifier: Intended Audience :: Developers
Classifier: License :: OSI Approved :: MIT License
Classifier: Topic :: Software Development :: Libraries
Classifier: Topic :: System :: Hardware
Requires-Python: >=3.7
License-File: LICENSE
Requires-Dist: smbus2 (>=0.4.2)
